setup_client.py
client/__init__.py
client/add_contact.py
client/client_database.py
client/del_contact.py
client/main_window.py
client/main_window_conv.py
client/start_dialog.py
client/transport.py
common/__init__.py
common/decos.py
common/descriptors.py
common/errors.py
common/metaclasses.py
common/utils.py
common/variables.py
demo_client.egg-info/PKG-INFO
demo_client.egg-info/SOURCES.txt
demo_client.egg-info/dependency_links.txt
demo_client.egg-info/requires.txt
demo_client.egg-info/top_level.txt
logs/__init__.py
logs/config_client_log.py
logs/config_global_log.py
logs/config_server_log.py